shareyourcloning_linkml/__init__.py
shareyourcloning_linkml/_version.py
shareyourcloning_linkml/datamodel/__init__.py
shareyourcloning_linkml/datamodel/_models.py
shareyourcloning_linkml/datamodel/models.py
shareyourcloning_linkml/schema/shareyourcloning_linkml.yaml
shareyourcloning_linkml-0.1.12a0.dist-info/LICENSE
shareyourcloning_linkml-0.1.12a0.dist-info/METADATA
shareyourcloning_linkml-0.1.12a0.dist-info/WHEEL
shareyourcloning_linkml-0.1.12a0.dist-info/RECORD
