Metadata-Version: 2.3
Name: shareyourcloning-linkml
Version: 0.1.12a0
Summary: A LinkML data model for ShareYourCloning
License: MIT
Author: Manuel Lera-Ramirez
Author-email: manuel.lera-ramirez@ucl.ac.uk
Requires-Python: >=3.9,<4.0
Classifier: Development Status :: 3 - Alpha
Classifier: Intended Audience :: Developers
Classifier: License :: OSI Approved :: MIT License
Classifier: Programming Language :: Python :: 3
Classifier: Programming Language :: Python :: 3.9
Classifier: Programming Language :: Python :: 3.10
Classifier: Programming Language :: Python :: 3.11
Classifier: Programming Language :: Python :: 3.12
Classifier: Programming Language :: Python :: 3.13
Provides-Extra: docs
Requires-Dist: pydantic (>=2.7.1,<3.0.0)
Project-URL: Documentation, https://genestorian.github.io/ShareYourCloning_LinkML
Project-URL: Homepage, https://github.com/genestorian/ShareYourCloning_LinkML
Project-URL: Repository, https://github.com/genestorian/ShareYourCloning_LinkML
